PySerpentine/__init__.py
PySerpentine/main.py
PySerLog-1.0.dist-info/METADATA
PySerLog-1.0.dist-info/WHEEL
PySerLog-1.0.dist-info/top_level.txt
PySerLog-1.0.dist-info/RECORD
